{"evaluationContainerEntity":{"trainingEvaluationEntity":{"dataResult":{"dataSourceID":"2B3B38B6-4204-4547-8DB7-DA40F2F773CB","itemsCount":39,"dataAnalysis":{"issues":[{"severity":"debug","description":"4 classes found, including Car, Chair, Table"},{"severity":"warning","description":"Less than 50 total images found - add more to improve model validation"},{"severity":"debug","description":"Smallest class is \"PC\" with 9 images"},{"description":"Largest class is \"Car\" with 10 images","severity":"debug"}],"classifierAnalysis":{"labelStats":{"PC":9,"Chair":10,"Table":10,"Car":10}},"summary":{"classCount":4,"sampleCount":39,"canUseValidation":0}},"dataURL":"file:\/\/\/Users\/hongseungpyo\/Desktop\/RealityObjectScan\/TrainingData\/","createdDate":"2024-05-30T12:13:05Z","classesCount":4},"createdDate":"2024-05-30T12:13:05Z","dataSourceID":"2B3B38B6-4204-4547-8DB7-DA40F2F773CB","id":"7c5df9ed-ec24-4ff9-b34d-26b8be3ddfa8","analysedDataType":"none","evaluationResult":{"imageClassifier":{"statsByLabel":{"PC":{"count":9,"precisionRecall":{"success":{"recall":1,"precision":1}}},"Chair":{"count":10,"precisionRecall":{"success":{"precision":1,"recall":1}}},"Car":{"count":10,"precisionRecall":{"success":{"recall":1,"precision":1}}},"Table":{"precisionRecall":{"success":{"precision":1,"recall":1}},"count":10}},"accuracy":1,"confusionMatrix":[{"actual":"Car","expected":"Car","count":10},{"actual":"Chair","expected":"Chair","count":10},{"actual":"PC","expected":"PC","count":9},{"actual":"Table","expected":"Table","count":10}]}}},"modifiedDate":"2024-05-30T12:14:01Z","validationEvaluationEntity":{"evaluationResult":{"imageClassifier":{"statsByLabel":{},"confusionMatrix":[],"accuracy":0}},"dataResult":{"createdDate":"2024-05-30T12:13:05Z"},"analysedDataType":"auto","id":"0b03e859-34c4-4af3-be6e-a17fa0e88898","createdDate":"2024-05-30T12:13:05Z"},"id":"933e2a50-acde-4b63-9781-33e48cf815f1","evaluationEntities":[{"dataResult":{},"analysedDataType":"none","id":"139e9463-3515-4529-89a6-7f97491c4cbf","createdDate":"2024-05-30T12:14:01Z"}],"testingEvaluationEntity":{"id":"fc11f261-a75b-4ae4-b0ff-67725d3b6b7d","createdDate":"2024-05-30T12:13:05Z","dataResult":{"createdDate":"2024-05-30T12:13:05Z"},"analysedDataType":"none"},"createdDate":"2024-05-30T12:14:01Z","previewType":"imageClassifier"},"activityEntities":["trainingStarted",[{"title":"Training Started","event":"trainingStarted","subtitle":"25 iterations","id":"0A7BC224-E48A-459E-9982-724EB69D70A4","createdDate":"2024-05-30T12:13:59Z"}],"trainingDataAdded",[{"title":"Training Data Added","id":"25899E0A-A9DA-41C4-9B9D-0E2D1E81946F","event":"trainingDataAdded","createdDate":"2024-05-30T12:13:23Z","subtitle":"TrainingData"}],"trainingFinished",[{"subtitle":"Model converged at 6 iterations","createdDate":"2024-05-30T12:14:00Z","id":"663FD2A9-16FF-4CB2-A538-787A662A62BC","title":"Training Completed","event":"trainingFinished"}],"experimentCreated",[{"createdDate":"2024-05-30T12:13:05Z","subtitle":"RealityObjectScanTrainingData","title":"Model Source Created","id":"A92EE0D1-CA3E-499B-A66E-8C6484621378","event":"experimentCreated"}]],"trainingEntity":{"validationResults":{"imageClassifier":{"statsByLabel":{},"accuracy":0,"confusionMatrix":[]}},"analysedDataType":"datasource","progress":[{"tableIndex":0,"count":2,"currentRowIndex":0,"percentComplete":0,"isLast":false,"tableDone":false,"icTrainingColumnHeader":{"trainingAccuracy":0.9487179487179487,"hasValidation":false,"elapsedTime":0.021471023559570312,"iterationCount":2,"validationAccuracy":0}},{"tableIndex":0,"percentComplete":0,"currentRowIndex":0,"count":3,"icTrainingColumnHeader":{"validationAccuracy":0,"hasValidation":false,"iterationCount":3,"elapsedTime":0.039674997329711914,"trainingAccuracy":1},"tableDone":false,"isLast":false},{"count":4,"isLast":false,"currentRowIndex":0,"percentComplete":0,"icTrainingColumnHeader":{"iterationCount":4,"validationAccuracy":0,"hasValidation":false,"elapsedTime":0.048063039779663086,"trainingAccuracy":1},"tableDone":false,"tableIndex":0},{"percentComplete":0,"count":5,"tableDone":false,"isLast":false,"icTrainingColumnHeader":{"hasValidation":false,"trainingAccuracy":1,"validationAccuracy":0,"iterationCount":5,"elapsedTime":0.06427502632141113},"tableIndex":0,"currentRowIndex":0},{"tableIndex":0,"count":6,"currentRowIndex":0,"percentComplete":0,"isLast":false,"tableDone":true,"icTrainingColumnHeader":{"iterationCount":6,"hasValidation":false,"elapsedTime":0.07323896884918213,"validationAccuracy":0,"trainingAccuracy":1}},{"count":10,"tableIndex":0,"currentRowIndex":0,"tableDone":false,"percentComplete":0,"isLast":false},{"tableDone":false,"isLast":false,"tableIndex":0,"currentRowIndex":0,"count":15,"percentComplete":0},{"tableIndex":0,"currentRowIndex":0,"isLast":false,"count":20,"percentComplete":0,"tableDone":false},{"tableIndex":0,"tableDone":false,"isLast":false,"count":25,"percentComplete":0,"currentRowIndex":0},{"count":30,"tableIndex":0,"currentRowIndex":0,"tableDone":false,"isLast":false,"percentComplete":0},{"tableDone":false,"tableIndex":0,"count":35,"currentRowIndex":0,"isLast":false,"percentComplete":0},{"count":39,"currentRowIndex":0,"isLast":false,"tableIndex":0,"tableDone":true,"percentComplete":0}],"finishTime":"2024-05-30T12:14:00Z","trainingAccuracy":1,"snapshottableCheckpoints":{"25":{"createdDate":"2024-05-30T12:14:00Z","modelURL":"file:\/\/\/Users\/hongseungpyo\/Library\/Caches\/com.apple.dt.createml\/projects\/FB0F6C57-5120-4B0A-A170-850CA854B552b15ca5e2250837b75ea288636dec643a27d08ae0\/sessions\/checkpoint.sessions\/E8311B01-C6FC-40B3-A788-1F7BD914D85F\/training-000000025.checkpoint.model\/checkpointModel.mlmodel","iteration":25}},"dataResult":{"dataAnalysis":{"classifierAnalysis":{"labelStats":{"PC":9,"Car":10,"Chair":10,"Table":10}},"summary":{"sampleCount":39,"classCount":4,"canUseValidation":0},"issues":[{"description":"4 classes found, including Car, Chair, Table","severity":"debug"},{"description":"Less than 50 total images found - add more to improve model validation","severity":"warning"},{"description":"Smallest class is \"PC\" with 9 images","severity":"debug"},{"description":"Largest class is \"Car\" with 10 images","severity":"debug"}]},"createdDate":"2024-05-30T12:13:05Z","dataSourceID":"2B3B38B6-4204-4547-8DB7-DA40F2F773CB","dataURL":"file:\/\/\/Users\/hongseungpyo\/Desktop\/RealityObjectScan\/TrainingData\/","itemsCount":39,"classesCount":4},"trainingResults":{"imageClassifier":{"accuracy":1,"confusionMatrix":[{"count":10,"actual":"Car","expected":"Car"},{"actual":"Chair","expected":"Chair","count":10},{"actual":"PC","expected":"PC","count":9},{"count":10,"actual":"Table","expected":"Table"}],"statsByLabel":{"Chair":{"count":10,"precisionRecall":{"success":{"recall":1,"precision":1}}},"PC":{"count":9,"precisionRecall":{"success":{"recall":1,"precision":1}}},"Car":{"count":10,"precisionRecall":{"success":{"recall":1,"precision":1}}},"Table":{"count":10,"precisionRecall":{"success":{"recall":1,"precision":1}}}}}},"resumableCheckpointURL":"Checkpoints\/E8311B01-C6FC-40B3-A788-1F7BD914D85F.RealityObjectScanTrainingData.checkpoint","snapshottableCheckpointModelURL":"Checkpoints\/E8311B01-C6FC-40B3-A788-1F7BD914D85F.RealityObjectScanTrainingData.checkpoint\/training-000000025.checkpoint.model\/checkpointModel.mlmodel","resumableCheckpoint":{"iteration":25,"checkpointURL":"file:\/\/\/Users\/hongseungpyo\/Library\/Caches\/com.apple.dt.createml\/projects\/FB0F6C57-5120-4B0A-A170-850CA854B552b15ca5e2250837b75ea288636dec643a27d08ae0\/sessions\/checkpoint.sessions\/E8311B01-C6FC-40B3-A788-1F7BD914D85F\/training-000000025.checkpoint","createdDate":"2024-05-30T12:14:00Z"},"checkpointMetrics":{"25":{"iteration":25,"metrics":{},"createdDate":"2024-05-30T12:14:00Z"}},"dataSourceID":"2B3B38B6-4204-4547-8DB7-DA40F2F773CB","featureExtractionCheckpointMayBeAvailable":false,"startTime":"2024-05-30T12:13:59Z","validationAccuracy":0},"createdDate":"2024-05-30T12:13:05Z","evaluationState":"uninitialized","evaluationEntity":{"analysedDataType":"none","id":"c74772d2-cdf8-4285-9bce-9163f097ed02","dataResult":{}},"modelEntity":{"createdDate":"2024-05-30T12:13:05Z","modelURL":"Models\/RealityObjectScanTrainingData.mlmodel","id":"7BAC0618-4D4C-4E20-A115-7C87EF783D20","modifiedDate":"2024-05-30T12:13:05Z","version":"1.0","title":"","preferredFilename":"","experimentID":"E8311B01-C6FC-40B3-A788-1F7BD914D85F"},"snapshotRole":{"withoutSnapshots":0},"contentDataResult":{"createdDate":"2024-05-30T12:13:05Z"},"modifiedDate":"2024-05-30T12:14:01Z","version":"1.0","settingEntity":{"algorithmType":"maxEnt","augmentations":[],"featureNames":[],"styleTransferAlgorithmType":"image","handActionClassifierAugmentations":[],"taskType":"imageClassifier","seedType":"default","harVideoAugmentations":0,"handPoseClassifierAugmentations":[],"featureExtractorType":"scenePrintV1","transferLearningEmbeddingType":"dynamic","iterationCount":25},"validationEntity":{"analysedDataType":"auto","dataResult":{"createdDate":"2024-05-30T12:13:05Z"}},"id":"E8311B01-C6FC-40B3-A788-1F7BD914D85F","preferredFilename":"RealityObjectScanTrainingData","state":"trained","title":"RealityObjectScanTrainingData 3"}